{
	"Python": {
		"Logo" : "static/logo/python.png",
		"Sous-sujet" : [
			{
				"Nom" : "Introduction",
				"Tutoriel" : {
					"Video" : "https://www.youtube.com/watch?v=cpPG0bKHYKc",
					"Tuteur" : "Keven1999"
				},
				"Quiz" : [
					{
						"Question" : "What is a correct syntax to output \"Hello World\" in Python?",
						"Choix" : ["echo \"Hello World\"", "p(\"Hello World\")", "print(\"Hello World\")","echo(\"Hello World\")"],
						"Reponse" : "print(\"Hello World\")"
					},
					{
						"Question" : "How do you insert COMMENTS in Python code?",
						"Choix" : ["//COMMENTAIRES",	"/*COMMENTAIRES*/", "#COMMENTAIRES"],
						"Reponse" : "#COMMENTAIRES"
					},
					{
						"Question" : "Which one is NOT a legal variable name?",
						"Choix" : ["my-var", "my_var", "_myvar", "Myvar"],
						"Reponse" : "my-var"
					},
					{
						"Question" : "How do you create a variable with the numeric value 5?",
						"Choix" : ["x = int(5)", "Both the other answers are correct", "x = 5"],
						"Reponse" : "Both the other answers are correct"
					},
					{
						"Question" : "In Python, 'Hello', is the same as \"Hello\"",
						"Choix" : ["True", "False"],
						"Reponse" : "True"
					}
				]
			},
			{
				"Nom" : "Syntax",
				"Quiz" : [
					{
						"Question" : "What is a correct syntax to output \"Hello World\" in Python?",
						"Choix" : ["echo \"Hello World\"", "p(\"Hello World\")", "print(\"Hello World\")","echo(\"Hello World\")"],
						"Reponse" : "print(\"Hello World\")"
					},
					{
						"Question" : "How do you insert COMMENTS in Python code?",
						"Choix" : ["//COMMENTAIRES",	"/*COMMENTAIRES*/", "#COMMENTAIRES"],
						"Reponse" : "#COMMENTAIRES"
					},
					{
						"Question" : "Which one is NOT a legal variable name?",
						"Choix" : ["my-var", "my_var", "_myvar", "Myvar"],
						"Reponse" : "my-var"
					},
					{
						"Question" : "How do you create a variable with the numeric value 5?",
						"Choix" : ["x = int(5)", "Both the other answers are correct", "x = 5"],
						"Reponse" : "Both the other answers are correct"
					},
					{
						"Question" : "In Python, 'Hello', is the same as \"Hello\"",
						"Choix" : ["True", "False"],
						"Reponse" : "True"
					}
				]
			},
			{
				"Nom" : "Language keywords"
			},
			{
				"Nom" : "Basic Types"
			},
			{
				"Nom" : "Operators"
			},
			{
				"Nom" : "Errors and Exceptions"
			},
			{
				"Nom" : "Classes"
			},
			{
				"Nom" : "Standard library"
			}
		]
	},

	"Java" : {
		"Logo" : "static/logo/java.png",
		"Sous-sujet" : []
	},

	"C" : {
		"Logo" : "static/logo/c.png",
		"Sous-sujet" : []
	},

	"Ruby" : {
		"Logo" : "static/logo/ruby.png",
		"Sous-sujet" : []
	},

	"Bash" : {
		"Logo" : "static/logo/bash.png",
		"Sous-sujet" : []
	},

	"PHP" : {
		"Logo" : "static/logo/php.png",
		"Sous-sujet" : []
	},

	"HTML" : {
		"Logo" : "static/logo/html.png",
		"Sous-sujet" : []
	},

	"Go" : {
		"Logo" : "static/logo/go.png",
		"Sous-sujet" : []
	},

	"Javascript" : {
		"Logo" : "static/logo/js.png",
		"Sous-sujet" : []
	},

	"Swift" : {
		"Logo" : "static/logo/swift.png",
		"Sous-sujet" : []
	},

	"Lua" : {
		"Logo" : "static/logo/lua.png",
		"Sous-sujet" : []
	},

	"C++" : {
		"Logo" : "static/logo/cplusplus.png",
		"Sous-sujet" : []
	},

	"C#" : {
		"Logo" : "static/logo/csharp.png",
		"Sous-sujet" : []
	}
}
